opentrons_analyze/__init__.py
opentrons_analyze/__main__.py
opentrons_analyze/analyze.py
opentrons_analyze-0.1.3.dist-info/METADATA
opentrons_analyze-0.1.3.dist-info/WHEEL
opentrons_analyze-0.1.3.dist-info/entry_points.txt
opentrons_analyze-0.1.3.dist-info/top_level.txt
opentrons_analyze-0.1.3.dist-info/RECORD
